[
  {
    "id": "https://www.eufunds.bg/bg/indicative-annual-work-programmes",
    "title": "Индикативни годишни работни програми",
    "source": "Еврофондове.бг",
    "category": "общи",
    "url": "https://www.eufunds.bg/bg/indicative-annual-work-programmes",
    "deadline": "",
    "found_at": "2026-06-27 14:47"
  },
  {
    "id": "https://eumis2020.government.bg/bg/s/Procedure/Active",
    "title": "Отворени процедури",
    "source": "Еврофондове.бг",
    "category": "общи",
    "url": "https://eumis2020.government.bg/bg/s/Procedure/Active",
    "deadline": "",
    "found_at": "2026-06-27 14:47"
  },
  {
    "id": "https://www.eufunds.bg/bg/tender-procedures",
    "title": "Процедури за избор на изпълнител",
    "source": "Еврофондове.бг",
    "category": "общи",
    "url": "https://www.eufunds.bg/bg/tender-procedures",
    "deadline": "",
    "found_at": "2026-06-27 14:47"
  },
  {
    "id": "https://www.eufunds.bg/bg/pmdr/term/565",
    "title": "Програмата за морско дело, рибарство и аквакултури",
    "source": "Еврофондове.бг",
    "category": "общи",
    "url": "https://www.eufunds.bg/bg/pmdr/term/565",
    "deadline": "",
    "found_at": "2026-06-27 14:47"
  },
  {
    "id": "https://www.mvr.bg/dmp/дейности/финансов-период-2021-2027/инструмент-за-ФПУ-2021-2027",
    "title": "Програма по Инструмента за финансова подкрепа за управлението на границите и визовата политика",
    "source": "Еврофондове.бг",
    "category": "общи",
    "url": "https://www.mvr.bg/dmp/дейности/финансов-период-2021-2027/инструмент-за-ФПУ-2021-2027",
    "deadline": "",
    "found_at": "2026-06-27 14:47"
  },
  {
    "id": "https://www.mvr.bg/dmp/дейности/финансов-период-2021-2027/фонд-вътрешна-сигурност-2021-2027",
    "title": "Програма по фонд „Вътрешна сигурност“",
    "source": "Еврофондове.бг",
    "category": "общи",
    "url": "https://www.mvr.bg/dmp/дейности/финансов-период-2021-2027/фонд-вътрешна-сигурност-2021-2027",
    "deadline": "",
    "found_at": "2026-06-27 14:47"
  },
  {
    "id": "https://www.mvr.bg/dmp/дейности/финансов-период-2021-2027/фонд-убежище-и-миграция-2021-2027",
    "title": "Програма по Фонд „Убежище, миграция и интеграция“",
    "source": "Еврофондове.бг",
    "category": "общи",
    "url": "https://www.mvr.bg/dmp/дейности/финансов-период-2021-2027/фонд-убежище-и-миграция-2021-2027",
    "deadline": "",
    "found_at": "2026-06-27 14:47"
  },
  {
    "id": "https://www.mrrb.bg/bg/infrastruktura-i-programi/programi-za-teritorialno-sutrudnichestvo-2021-2027/",
    "title": "Програми за териториално сътрудничество",
    "source": "Еврофондове.бг",
    "category": "общи",
    "url": "https://www.mrrb.bg/bg/infrastruktura-i-programi/programi-za-teritorialno-sutrudnichestvo-2021-2027/",
    "deadline": "",
    "found_at": "2026-06-27 14:47"
  },
  {
    "id": "https://www.eufunds.bg/bg/taxonomy/term/904",
    "title": "Програма за научни изследвания, иновации и дигитализация за интелигентна трансформация",
    "source": "Еврофондове.бг",
    "category": "общи",
    "url": "https://www.eufunds.bg/bg/taxonomy/term/904",
    "deadline": "",
    "found_at": "2026-06-27 14:47"
  },
  {
    "id": "https://www.eufunds.bg/bg/taxonomy/term/1462",
    "title": "Програмата за храни и основно материално подпомагане",
    "source": "Еврофондове.бг",
    "category": "общи",
    "url": "https://www.eufunds.bg/bg/taxonomy/term/1462",
    "deadline": "",
    "found_at": "2026-06-27 14:47"
  },
  {
    "id": "https://www.eufunds.bg/bg/taxonomy/term/912",
    "title": "Финансиране в област “Вътрешни работи” 2021-2027",
    "source": "Еврофондове.бг",
    "category": "общи",
    "url": "https://www.eufunds.bg/bg/taxonomy/term/912",
    "deadline": "",
    "found_at": "2026-06-27 14:47"
  },
  {
    "id": "https://www.eufunds.bg/bg/taxonomy/term/1199",
    "title": "Покани за избор на ЮЛНЦ в състава на Комитетите за наблюдение",
    "source": "Еврофондове.бг",
    "category": "общи",
    "url": "https://www.eufunds.bg/bg/taxonomy/term/1199",
    "deadline": "",
    "found_at": "2026-06-27 14:47"
  },
  {
    "id": "https://www.eufunds.bg/bg/pmdr",
    "title": "Програма за морско дело и рибарство",
    "source": "Еврофондове.бг",
    "category": "общи",
    "url": "https://www.eufunds.bg/bg/pmdr",
    "deadline": "",
    "found_at": "2026-06-27 14:47"
  },
  {
    "id": "https://www.eufunds.bg/bg/prsr",
    "title": "Програма за развитие на селските райони",
    "source": "Еврофондове.бг",
    "category": "общи",
    "url": "https://www.eufunds.bg/bg/prsr",
    "deadline": "",
    "found_at": "2026-06-27 14:47"
  },
  {
    "id": "https://www.mrrb.bg/bg/infrastruktura-i-programi/programi-za-teritorialno-sutrudnichestvo-2014-2020/",
    "title": "Програми за териториално сътрудничество 2014-2020",
    "source": "Еврофондове.бг",
    "category": "общи",
    "url": "https://www.mrrb.bg/bg/infrastruktura-i-programi/programi-za-teritorialno-sutrudnichestvo-2014-2020/",
    "deadline": "",
    "found_at": "2026-06-27 14:47"
  },
  {
    "id": "https://www.mzh.government.bg/bg/politiki-i-programi/",
    "title": "Политики и програми",
    "source": "Министерство на земеделието",
    "category": "земеделие",
    "url": "https://www.mzh.government.bg/bg/politiki-i-programi/",
    "deadline": "",
    "found_at": "2026-06-27 14:47"
  },
  {
    "id": "https://www.mzh.government.bg/bg/politiki-i-programi/programi-za-finansirane/",
    "title": "Програми за финансиране",
    "source": "Министерство на земеделието",
    "category": "земеделие",
    "url": "https://www.mzh.government.bg/bg/politiki-i-programi/programi-za-finansirane/",
    "deadline": "",
    "found_at": "2026-06-27 14:47"
  },
  {
    "id": "https://www.mzh.government.bg/bg/politiki-i-programi/programi-za-finansirane/programa-za-razvitie-na-selskite-rayoni/",
    "title": "Програма за развитие на селските райони",
    "source": "Министерство на земеделието",
    "category": "земеделие",
    "url": "https://www.mzh.government.bg/bg/politiki-i-programi/programi-za-finansirane/programa-za-razvitie-na-selskite-rayoni/",
    "deadline": "",
    "found_at": "2026-06-27 14:47"
  },
  {
    "id": "https://www.mzh.government.bg/bg/politiki-i-programi/programi-za-finansirane/programa-za-morsko-delo-i-ribarstvo/",
    "title": "Програма за морско дело и рибарство",
    "source": "Министерство на земеделието",
    "category": "земеделие",
    "url": "https://www.mzh.government.bg/bg/politiki-i-programi/programi-za-finansirane/programa-za-morsko-delo-i-ribarstvo/",
    "deadline": "",
    "found_at": "2026-06-27 14:47"
  }
]